pillar/__init__.py
pillar/client.py
pillar_api_wrapper-0.0.2.dist-info/LICENSE
pillar_api_wrapper-0.0.2.dist-info/METADATA
pillar_api_wrapper-0.0.2.dist-info/WHEEL
pillar_api_wrapper-0.0.2.dist-info/top_level.txt
pillar_api_wrapper-0.0.2.dist-info/RECORD
