Metadata-Version: 2.1
Name: pillar-api-wrapper
Version: 0.0.2
Summary: Python wrapper for our REST API.
Home-page: https://github.com/pillargg/pillar-api-wrapper
Author: PillarGG
Author-email: opensource@pillar.gg
License: UNKNOWN
Platform: UNKNOWN
Classifier: Programming Language :: Python :: 3
Classifier: License :: OSI Approved :: MIT License
Classifier: Operating System :: OS Independent
Requires-Python: >=3.6
Requires-Dist: requests (>=2.25.0)
